sslcommerz_sdk/__init__.py
sslcommerz_sdk/enums.py
sslcommerz_sdk/exceptions.py
sslcommerz_sdk/handlers.py
sslcommerz_sdk/services.py
sslcommerz_sdk/store.py
sslcommerz_sdk/store_providers.py
sslcommerz_sdk/contrib/django_app/__init__.py
sslcommerz_sdk/contrib/django_app/apps.py
sslcommerz_sdk/contrib/django_app/models.py
sslcommerz_sdk/contrib/django_app/migrations/0001_initial.py
sslcommerz_sdk/contrib/django_app/migrations/__init__.py
sslcommerz_sdk/orm_adapters/__init__.py
sslcommerz_sdk/orm_adapters/base.py
sslcommerz_sdk/orm_adapters/django.py
sslcommerz_sdk/orm_adapters/pynamodb.py
sslcommerz_sdk/orm_adapters/sqlalchemy.py
sslcommerz_sdk-1.0.4.dist-info/LICENSE
sslcommerz_sdk-1.0.4.dist-info/METADATA
sslcommerz_sdk-1.0.4.dist-info/WHEEL
sslcommerz_sdk-1.0.4.dist-info/top_level.txt
sslcommerz_sdk-1.0.4.dist-info/RECORD
